zhon/__init__.py
zhon/hanzi.py
zhon/pinyin.py
zhon/zhuyin.py
zhon/cedict/__init__.py
zhon/cedict/all.py
zhon/cedict/simplified.py
zhon/cedict/traditional.py
zhon-2.0.1.dist-info/METADATA
zhon-2.0.1.dist-info/WHEEL
zhon-2.0.1.dist-info/licenses/AUTHORS.rst
zhon-2.0.1.dist-info/licenses/LICENSE.txt
zhon-2.0.1.dist-info/RECORD
