Metadata-Version: 2.1
Name: zhon
Version: 2.0.1
Summary: Zhon provides constants used in Chinese text processing.
Project-URL: Documentation, https://tsroten.github.io/fcache
Project-URL: Source code, https://github.com/tsroten/zhon
Author-email: Thomas Roten <thomas@roten.us>
License-Expression: MIT
License-File: AUTHORS.rst
License-File: LICENSE.txt
Keywords: cc-cedict,cedict,characters,chinese,cjk,han,hanzi,mandarin,pinyin,punctuation,radicals,segmentation,simplified,tokenization,traditional,unicode,zhuyin
Classifier: Development Status :: 5 - Production/Stable
Classifier: Intended Audience :: Developers
Classifier: License :: OSI Approved :: MIT License
Classifier: Operating System :: OS Independent
Classifier: Programming Language :: Python
Classifier: Programming Language :: Python :: 3
Classifier: Programming Language :: Python :: 3.7
Classifier: Programming Language :: Python :: 3.8
Classifier: Programming Language :: Python :: 3.9
Classifier: Programming Language :: Python :: 3.10
Classifier: Programming Language :: Python :: 3.11
Classifier: Topic :: Software Development :: Libraries :: Python Modules
Classifier: Topic :: Text Processing :: Linguistic
Requires-Python: >=3.7
